[
  {
    "symbol": "CL=F",
    "name": "WTI Crude",
    "unit": "$/bbl",
    "price": 83.8,
    "dayChange": -13.22,
    "weekChange": -13.22,
    "history": [
      96.56999969482422,
      99.08000183105469,
      91.27999877929688,
      91.29000091552734,
      94.69000244140625,
      83.80000305175781
    ]
  },
  {
    "symbol": "BZ=F",
    "name": "Brent Crude",
    "unit": "$/bbl",
    "price": 91.4,
    "dayChange": -3.99,
    "weekChange": -3.99,
    "history": [
      95.19999694824219,
      99.36000061035156,
      94.79000091552734,
      94.93000030517578,
      99.38999938964844,
      91.4000015258789
    ]
  },
  {
    "symbol": "NG=F",
    "name": "Natural Gas",
    "unit": "$/MMBtu",
    "price": 2.675,
    "dayChange": 1.02,
    "weekChange": 1.02,
    "history": [
      2.6480000019073486,
      2.627000093460083,
      2.5989999771118164,
      2.609999895095825,
      2.6470000743865967,
      2.674999952316284
    ]
  },
  {
    "symbol": "GC=F",
    "name": "Gold",
    "unit": "$/oz",
    "price": 4853.4,
    "dayChange": 1.92,
    "weekChange": 1.92,
    "history": [
      4761.89990234375,
      4742.39990234375,
      4825,
      4800,
      4785.39990234375,
      4853.39990234375
    ]
  },
  {
    "symbol": "SI=F",
    "name": "Silver",
    "unit": "$/oz",
    "price": 81.04,
    "dayChange": 6.18,
    "weekChange": 6.18,
    "history": [
      76.3239974975586,
      75.52300262451172,
      79.39099884033203,
      79.49099731445312,
      78.60600280761719,
      81.04000091552734
    ]
  },
  {
    "symbol": "HO=F",
    "name": "Heating Oil",
    "unit": "$/gal",
    "price": 3.3409,
    "dayChange": -11.18,
    "weekChange": -11.18,
    "history": [
      3.7616000175476074,
      3.8341000080108643,
      3.624300003051758,
      3.753200054168701,
      3.832900047302246,
      3.34089994430542
    ]
  },
  {
    "symbol": "RB=F",
    "name": "Gasoline",
    "unit": "$/gal",
    "price": 2.941,
    "dayChange": -3.17,
    "weekChange": -3.17,
    "history": [
      3.0373001098632812,
      3.115999937057495,
      3.0394999980926514,
      3.069200038909912,
      3.1637001037597656,
      2.940999984741211
    ]
  }
]