[
  {
    "symbol": "CL=F",
    "name": "WTI Crude",
    "unit": "$/bbl",
    "price": 104.89,
    "dayChange": 12.83,
    "weekChange": 12.83,
    "history": [
      92.95999908447266,
      95.8499984741211,
      94.4000015258789,
      96.37000274658203,
      99.93000030517578,
      104.88999938964844
    ]
  },
  {
    "symbol": "BZ=F",
    "name": "Brent Crude",
    "unit": "$/bbl",
    "price": 109.49,
    "dayChange": 7.44,
    "weekChange": 7.44,
    "history": [
      101.91000366210938,
      105.06999969482422,
      105.33000183105469,
      108.2300033569336,
      111.26000213623047,
      109.48999786376953
    ]
  },
  {
    "symbol": "NG=F",
    "name": "Natural Gas",
    "unit": "$/MMBtu",
    "price": 2.649,
    "dayChange": -2.68,
    "weekChange": -2.68,
    "history": [
      2.7219998836517334,
      2.614000082015991,
      2.5230000019073486,
      2.549999952316284,
      2.559000015258789,
      2.6489999294281006
    ]
  },
  {
    "symbol": "GC=F",
    "name": "Gold",
    "unit": "$/oz",
    "price": 4547.2,
    "dayChange": -3.92,
    "weekChange": -3.92,
    "history": [
      4732.5,
      4705.10009765625,
      4722.2998046875,
      4675.39990234375,
      4591.5,
      4547.2001953125
    ]
  },
  {
    "symbol": "SI=F",
    "name": "Silver",
    "unit": "$/oz",
    "price": 72.35,
    "dayChange": -7.12,
    "weekChange": -7.12,
    "history": [
      77.89299774169922,
      75.46499633789062,
      76.38300323486328,
      75.00299835205078,
      73.20500183105469,
      72.3499984741211
    ]
  },
  {
    "symbol": "HO=F",
    "name": "Heating Oil",
    "unit": "$/gal",
    "price": 4.046,
    "dayChange": 2.75,
    "weekChange": 2.75,
    "history": [
      3.9379000663757324,
      3.9881999492645264,
      3.887399911880493,
      3.9746999740600586,
      3.9711999893188477,
      4.046000003814697
    ]
  },
  {
    "symbol": "RB=F",
    "name": "Gasoline",
    "unit": "$/gal",
    "price": 3.5588,
    "dayChange": 5.98,
    "weekChange": 5.98,
    "history": [
      3.3578999042510986,
      3.462100028991699,
      3.462599992752075,
      3.490999937057495,
      3.5604000091552734,
      3.558799982070923
    ]
  }
]