[
  {
    "symbol": "CL=F",
    "name": "WTI Crude",
    "unit": "$/bbl",
    "price": 101.23,
    "dayChange": 3.22,
    "weekChange": 3.22,
    "history": [
      98.06999969482422,
      102.18000030517578,
      101.0199966430664,
      101.16999816894531,
      105.41999816894531,
      101.2300033569336
    ]
  },
  {
    "symbol": "BZ=F",
    "name": "Brent Crude",
    "unit": "$/bbl",
    "price": 109.28,
    "dayChange": 4.87,
    "weekChange": 4.87,
    "history": [
      104.20999908447266,
      107.7699966430664,
      105.62999725341797,
      105.72000122070312,
      109.26000213623047,
      109.27999877929688
    ]
  },
  {
    "symbol": "NG=F",
    "name": "Natural Gas",
    "unit": "$/MMBtu",
    "price": 3.016,
    "dayChange": 3.64,
    "weekChange": 3.64,
    "history": [
      2.9100000858306885,
      2.8429999351501465,
      2.864000082015991,
      2.8940000534057617,
      2.9600000381469727,
      3.0160000324249268
    ]
  },
  {
    "symbol": "GC=F",
    "name": "Gold",
    "unit": "$/oz",
    "price": 4563.9,
    "dayChange": -3.28,
    "weekChange": -3.28,
    "history": [
      4718.7001953125,
      4677.60009765625,
      4697.7001953125,
      4678.10009765625,
      4555.7998046875,
      4563.89990234375
    ]
  },
  {
    "symbol": "SI=F",
    "name": "Silver",
    "unit": "$/oz",
    "price": 77.425,
    "dayChange": -9.43,
    "weekChange": -9.43,
    "history": [
      85.48500061035156,
      85.12999725341797,
      88.88800048828125,
      84.91200256347656,
      77.16100311279297,
      77.42500305175781
    ]
  },
  {
    "symbol": "HO=F",
    "name": "Heating Oil",
    "unit": "$/gal",
    "price": 3.9774,
    "dayChange": 0.22,
    "weekChange": 0.22,
    "history": [
      3.968600034713745,
      4.15880012512207,
      3.9667000770568848,
      3.905600070953369,
      4.053400039672852,
      3.977400064468384
    ]
  },
  {
    "symbol": "RB=F",
    "name": "Gasoline",
    "unit": "$/gal",
    "price": 3.569,
    "dayChange": -0.86,
    "weekChange": -0.86,
    "history": [
      3.5998001098632812,
      3.697700023651123,
      3.6187000274658203,
      3.6057000160217285,
      3.701900005340576,
      3.569000005722046
    ]
  }
]